mdbackup/__init__.py
mdbackup/__main__.py
mdbackup/archive.py
mdbackup/hooks.py
mdbackup/jsonschemavalidator.py
mdbackup/utils.py
mdbackup/_commands/__init__.py
mdbackup/_commands/backup.py
mdbackup/_commands/cleanup.py
mdbackup/_commands/upload.py
mdbackup/actions/__init__.py
mdbackup/actions/container.py
mdbackup/actions/ds.py
mdbackup/actions/runner.py
mdbackup/actions/builtin/__init__.py
mdbackup/actions/builtin/_os_utils.py
mdbackup/actions/builtin/_register.py
mdbackup/actions/builtin/archive.py
mdbackup/actions/builtin/command.py
mdbackup/actions/builtin/compress.py
mdbackup/actions/builtin/database.py
mdbackup/actions/builtin/directory.py
mdbackup/actions/builtin/encrypt.py
mdbackup/actions/builtin/file.py
mdbackup/actions/builtin/network.py
mdbackup/check_packages/__init__.py
mdbackup/config/__init__.py
mdbackup/config/cloud.py
mdbackup/config/configuration.py
mdbackup/config/secret.py
mdbackup/config/storage.py
mdbackup/json-schemas/cloud.compression.schema.json
mdbackup/json-schemas/cloud.encrypt.schema.json
mdbackup/json-schemas/cloud.providers.b2.schema.json
mdbackup/json-schemas/cloud.providers.base.schema.json
mdbackup/json-schemas/cloud.providers.ftp.schema.json
mdbackup/json-schemas/cloud.providers.ftps.schema.json
mdbackup/json-schemas/cloud.providers.gdrive.schema.json
mdbackup/json-schemas/cloud.providers.s3.schema.json
mdbackup/json-schemas/cloud.providers.schema.json
mdbackup/json-schemas/cloud.providers.sftp.schema.json
mdbackup/json-schemas/config.schema.json
mdbackup/json-schemas/hooks.schema.json
mdbackup/json-schemas/secrets.base.schema.json
mdbackup/json-schemas/secrets.file.schema.json
mdbackup/json-schemas/secrets.vault.schema.json
mdbackup/secrets/__init__.py
mdbackup/secrets/file_backend.py
mdbackup/secrets/secrets.py
mdbackup/secrets/vault_backend.py
mdbackup/storage/__init__.py
mdbackup/storage/backblaze.py
mdbackup/storage/drive.py
mdbackup/storage/ftp.py
mdbackup/storage/s3.py
mdbackup/storage/sftp.py
mdbackup/storage/storage.py
mdbackup-0.4.3.dist-info/LICENSE
mdbackup-0.4.3.dist-info/METADATA
mdbackup-0.4.3.dist-info/WHEEL
mdbackup-0.4.3.dist-info/entry_points.txt
mdbackup-0.4.3.dist-info/top_level.txt
mdbackup-0.4.3.dist-info/RECORD
