Metadata-Version: 2.1
Name: mdbackup
Version: 0.4.3
Summary: Small but customizable utility to create backups and store them in cloud storage providers
Home-page: https://github.com/majorcadevs/mdbackup
Author: majorcadevs (melchor9000 & amgxv)
Author-email: melchor9000@gmail.com
License: UNKNOWN
Platform: UNKNOWN
Classifier: Intended Audience :: System Administrators
Classifier: License :: OSI Approved :: GNU General Public License v3 (GPLv3)
Classifier: Operating System :: MacOS :: MacOS X
Classifier: Operating System :: Unix
Classifier: Operating System :: POSIX :: Linux
Classifier: Programming Language :: Python :: 3.6
Classifier: Programming Language :: Python :: 3.7
Classifier: Programming Language :: Python :: 3.8
Classifier: Topic :: System :: Recovery Tools
Classifier: Topic :: Utilities
Classifier: Development Status :: 5 - Production/Stable
Requires-Dist: pyyaml
Requires-Dist: jsonschema
